{
    "початок_сесії": "2025-09-14 14:20:54.090063",
    "події": [
        {
            "крок": 1,
            "функція": "add",
            "аргументи": [
                5,
                6
            ],
            "ключові_аргументи": {},
            "час": "2025-09-14 14:20:54.090112",
            "статус": "успіх",
            "результат": 11
        },
        {
            "крок": 2,
            "функція": "minus",
            "аргументи": [
                5,
                2
            ],
            "ключові_аргументи": {},
            "час": "2025-09-14 14:20:54.090334",
            "статус": "успіх",
            "результат": 3
        },
        {
            "крок": 3,
            "функція": "multiply",
            "аргументи": [
                2,
                10
            ],
            "ключові_аргументи": {},
            "час": "2025-09-14 14:20:54.090492",
            "статус": "успіх",
            "результат": 20
        },
        {
            "крок": 4,
            "функція": "divide",
            "аргументи": [
                5,
                0
            ],
            "ключові_аргументи": {},
            "час": "2025-09-14 14:20:54.090641",
            "статус": "помилка",
            "результат": null
        }
    ],
    "помилка": {
        "тип": "ZeroDivisionError",
        "повідомлення": "division by zero",
        "traceback": "Traceback (most recent call last):\n  File \"e:\\Python-Logger-Tracker\\logger_setup.py\", line 35, in wrapper\n    result = func(*args, **kwargs)\n  File \"e:\\Python-Logger-Tracker\\main.py\", line 18, in divide\n    return a / b\n           ~~^~~\nZeroDivisionError: division by zero\n",
        "файл": "e:\\Python-Logger-Tracker\\main.py",
        "рядок": 18,
        "фрагмент_коду": [
            {
                "рядок": 15,
                "код": "",
                "помилка": false
            },
            {
                "рядок": 16,
                "код": "@log_function",
                "помилка": false
            },
            {
                "рядок": 17,
                "код": "def divide(a, b):",
                "помилка": false
            },
            {
                "рядок": 18,
                "код": "    return a / b",
                "помилка": true
            },
            {
                "рядок": 19,
                "код": "",
                "помилка": false
            },
            {
                "рядок": 20,
                "код": "# ! ===================== Виклики функцій =====================",
                "помилка": false
            },
            {
                "рядок": 21,
                "код": "if __name__ == \"__main__\":",
                "помилка": false
            }
        ],
        "локальні_змінні": {
            "a": "5",
            "b": "0"
        },
        "у_якій_функції": "divide",
        "крок": 4,
        "час": "2025-09-14 14:20:54.096819"
    }
}